nonebot_plugin_icey/__init__.py
nonebot_plugin_icey/config.py
nonebot_plugin_icey/common/__init__.py
nonebot_plugin_icey/common/dao.py
nonebot_plugin_icey/common/hooks.py
nonebot_plugin_icey/common/matcher.py
nonebot_plugin_icey/common/models.py
nonebot_plugin_icey/common/service.py
nonebot_plugin_icey/common/locales/__init__.py
nonebot_plugin_icey/modules/blacklist/__init__.py
nonebot_plugin_icey/modules/blacklist/matcher.py
nonebot_plugin_icey/modules/blacklist/model.py
nonebot_plugin_icey/modules/debuger/__init__.py
nonebot_plugin_icey/modules/filters/__init__.py
nonebot_plugin_icey/modules/filters/matcher.py
nonebot_plugin_icey/modules/filters/model.py
nonebot_plugin_icey/modules/filters/service.py
nonebot_plugin_icey/modules/help/__init__.py
nonebot_plugin_icey/modules/help/matcher.py
nonebot_plugin_icey/modules/request/__init__.py
nonebot_plugin_icey/modules/request/matcher.py
nonebot_plugin_icey/modules/temp/__init__.py
nonebot_plugin_icey/modules/temp/matcher.py
nonebot_plugin_icey/modules/temp/model.py
nonebot_plugin_icey/modules/temp/service.py
nonebot_plugin_icey/modules/verify/__init__.py
nonebot_plugin_icey/modules/verify/matcher.py
nonebot_plugin_icey/modules/verify/model.py
nonebot_plugin_icey/modules/verify/service.py
nonebot_plugin_icey/modules/welcome/__init__.py
nonebot_plugin_icey/modules/welcome/matcher.py
nonebot_plugin_icey/modules/welcome/model.py
nonebot_plugin_icey/modules/welcome/service.py
nonebot_plugin_icey-0.1.4.dist-info/licenses/LICENSE
nonebot_plugin_icey-0.1.4.dist-info/METADATA
nonebot_plugin_icey-0.1.4.dist-info/WHEEL
nonebot_plugin_icey-0.1.4.dist-info/top_level.txt
nonebot_plugin_icey-0.1.4.dist-info/RECORD
