Metadata-Version: 2.4
Name: nonebot-plugin-icey
Version: 0.1.4
Summary: Icey QQ群管助手
Requires-Python: <4.0,>=3.9
License-File: LICENSE
Requires-Dist: nonebot2[fastapi]>=2.4.4
Requires-Dist: nonebot2[httpx]>=2.4.4
Requires-Dist: nonebot2[websockets]>=2.4.4
Requires-Dist: nonebot-adapter-onebot>=2.4.6
Requires-Dist: nonebot-adapter-telegram>=0.1.0b20
Requires-Dist: nonebot-plugin-orm[mysql,postgresql,sqlite]>=0.8.3
Provides-Extra: dev
Requires-Dist: pyright[nodejs]; extra == "dev"
Requires-Dist: ruff; extra == "dev"
Dynamic: license-file
